{"stat.chestOpened":6,"stat.walkOneCm":263915,"stat.playerKills":1,"achievement.openInventory":29,"stat.leaveGame":4,"stat.damageTaken":10522,"stat.useItem.minecraft.tnt":19,"stat.flyOneCm":101931,"stat.deaths":2,"stat.drop":1,"stat.jump":404,"stat.playOneMinute":42535,"stat.fallOneCm":44531,"stat.useItem.minecraft.wooden_sword":3,"stat.damageDealt":214,"stat.crouchOneCm":8360,"stat.useItem.minecraft.wool":20,"stat.timeSinceDeath":2657,"stat.sprintOneCm":101561,"achievement.exploreAllBiomes":{"value":0,"progress":["Mega Taiga Hills","Roofed Forest","Jungle","Forest","River","Plains","Taiga","Mega Taiga"]}}