{"stat.chestOpened":21,"stat.walkOneCm":231623,"stat.playerKills":3,"stat.useItem.minecraft.stone":42,"stat.leaveGame":8,"stat.jump":706,"stat.swimOneCm":101,"stat.fallOneCm":18512,"stat.useItem.minecraft.planks":7,"stat.crouchOneCm":1309,"stat.mineBlock.minecraft.chest":1,"stat.sprintOneCm":164578,"achievement.exploreAllBiomes":{"value":0,"progress":["Mesa","Jungle","Forest","Savanna"]},"achievement.openInventory":7,"stat.useItem.minecraft.iron_sword":13,"stat.damageTaken":393371,"stat.useItem.minecraft.wooden_shovel":2,"stat.flyOneCm":213811,"stat.deaths":5,"stat.playOneMinute":41489,"stat.damageDealt":1225,"stat.timeSinceDeath":11685,"stat.useItem.minecraft.wooden_axe":1,"stat.mineBlock.minecraft.dirt":6,"stat.diveOneCm":609}