{"stat.chestOpened":1,"stat.useItem.minecraft.bow":7,"stat.flyOneCm":3530,"stat.walkOneCm":19194,"stat.jump":34,"stat.playerKills":1,"stat.playOneMinute":4468,"stat.fallOneCm":1955,"achievement.openInventory":3,"stat.damageTaken":20,"stat.useItem.minecraft.diamond_axe":4,"stat.useItem.minecraft.cobblestone":10,"stat.damageDealt":140,"stat.crouchOneCm":281,"stat.mineBlock.minecraft.chest":3,"stat.timeSinceDeath":4468,"stat.sprintOneCm":4097,"achievement.exploreAllBiomes":{"value":0,"progress":["Mesa","Jungle","Savanna"]}}